Verilog/Circular Fifo/fifo.v
// Circular-queue-based Fifo
`timescale 1ns/1ps
module fifo # (
    parameter B = 8, // number of bits in a word
    W = 4 // number of address bits
  )
  (
    input wire clk, reset,
    input wire rd, wr,
    input wire [B-1:0] w_data,
    output wire empty, full,
    output wire [B-1:0] r_data
  );

  // Signal Declaration
  reg [B-1:0] array_reg [2**W-1:0]; // register array
  reg [W-1:0] w_ptr_reg, w_ptr_next, w_ptr_succ;
  reg [W-1:0] r_ptr_reg, r_ptr_next, r_ptr_succ;
  reg full_reg, empty_reg, full_next, empty_next;

  wire wr_en;

  // Write Operation
  always@(posedge clk)
    if (wr_en)
      array_reg[w_ptr_reg] <= w_data;

  // Read Operation
  assign r_data = array_reg[r_ptr_reg];

  // write enable when fifo is not full
  assign wr_en = wr & ~full_reg;

  // fifo control logic
  // register for read and write pointers
  always@(posedge clk, posedge reset)
    if(reset)
    begin
      w_ptr_reg <= 0;
      r_ptr_reg <= 0;
      full_reg <= 1'b0;
      empty_reg <= 1'b1;
    end
    else
    begin
      w_ptr_reg <= w_ptr_next;
      r_ptr_reg <= r_ptr_next;
      full_reg <= full_next;
      empty_reg <= empty_next;
    end

  // next state logic for read and write pointers
  always@(*)
  begin
    w_ptr_succ = w_ptr_reg + 1;
    r_ptr_succ = r_ptr_reg + 1;
    w_ptr_next = w_ptr_reg;
    r_ptr_next = r_ptr_reg;
    full_next = full_reg;
    empty_next = empty_reg;
    case({wr,rd})
      2'b01:  // write 
        if(~empty_reg)
        begin
          r_ptr_next = r_ptr_succ;
          full_next = 1'b0;
          if (r_ptr_succ == w_ptr_reg)
            empty_next = 1'b1;
        end

      2'b10:  // read
        if(~full_reg)
        begin
          w_ptr_next = w_ptr_succ;
          empty_next = 1'b0;
          if (w_ptr_succ == r_ptr_reg)
            full_next = 1'b1;
        end

      2'b11:
      begin
        w_ptr_next = w_ptr_succ;
        r_ptr_next = r_ptr_succ;
      end
    endcase
  end

  assign full = full_reg;
  assign empty = empty_reg;

endmodule

Verilog/Circular Fifo/tb.v

module fifo_tb;

  // Parameters
  localparam  B = 8;
  localparam  W = 4;

  //Ports
  reg clk, reset;
  reg rd,  wr;
  reg [B-1:0] w_data;
  wire empty, full;
  wire [B-1:0] r_data;

  fifo uut (
    .clk(clk),
    .reset(reset),
    .rd(rd),
    .wr(wr),
    .w_data(w_data),
    .empty(empty),
    .full(full),
    .r_data(r_data)
  );

  always #5  clk = ! clk ;
  initial begin
    $dumpfile("dump.vcd");
    $dumpvars(0,fifo_tb);

    clk = 0;
    reset = 1;
    rd = 0; wr = 0;
    #5 reset = 0;
    // writing 1,2,3,4,5
    #5 w_data = 1; wr = 1;
    #30 w_data = 2; wr = 1;
    #10 wr = 0;
    //#10 w_data = 3; wr = 1;
    //#10 w_data = 4; wr = 1;
    //#10 w_data = 5; wr = 1;
    #30 rd = 1;    
    
    #50 $finish;

  end
  

endmodule

Verilog/Circular Fifo/dump.vcd
$date
	Wed Jan 10 17:19:27 2024
$end
$version
	Icarus Verilog
$end
$timescale
	1ps
$end
$scope module fifo_tb $end
$var wire 8 ! r_data [7:0] $end
$var wire 1 " full $end
$var wire 1 # empty $end
$var reg 1 $ clk $end
$var reg 1 % rd $end
$var reg 1 & reset $end
$var reg 8 ' w_data [7:0] $end
$var reg 1 ( wr $end
$scope module uut $end
$var wire 1 $ clk $end
$var wire 1 # empty $end
$var wire 1 " full $end
$var wire 8 ) r_data [7:0] $end
$var wire 1 % rd $end
$var wire 1 & reset $end
$var wire 8 * w_data [7:0] $end
$var wire 1 ( wr $end
$var wire 1 + wr_en $end
$var reg 1 , empty_next $end
$var reg 1 - empty_reg $end
$var reg 1 . full_next $end
$var reg 1 / full_reg $end
$var reg 4 0 r_ptr_next [3:0] $end
$var reg 4 1 r_ptr_reg [3:0] $end
$var reg 4 2 r_ptr_succ [3:0] $end
$var reg 4 3 w_ptr_next [3:0] $end
$var reg 4 4 w_ptr_reg [3:0] $end
$var reg 4 5 w_ptr_succ [3:0] $end
$upscope $end
$upscope $end
$enddefinitions $end
#0
$dumpvars
b1 5
b0 4
b0 3
b1 2
b0 1
b0 0
0/
0.
1-
1,
0+
bx *
bx )
0(
bx '
1&
0%
0$
1#
0"
bx !
$end
#5000
0&
1$
#10000
1+
0,
b1 3
1(
b1 '
b1 *
0$
#15000
b10 3
b10 5
0#
0-
b1 4
b1 !
b1 )
1$
#20000
0$
#25000
b11 3
b11 5
b10 4
1$
#30000
0$
#35000
b100 3
b100 5
b11 4
1$
#40000
0$
b10 '
b10 *
#45000
b101 3
b101 5
b100 4
1$
#50000
0+
b100 3
0$
0(
#55000
1$
#60000
0$
#65000
1$
#70000
0$
#75000
1$
#80000
b1 0
0$
1%
#85000
b10 0
b10 2
b1 1
1$
#90000
0$
#95000
b11 0
b11 2
b10 1
1$
#100000
0$
#105000
1,
b100 0
b100 2
b10 !
b10 )
b11 1
1$
#110000
0$
#115000
b101 2
1#
1-
bx !
bx )
b100 1
1$
