Verilog/Sign Adder/sign_adder.v
module sign_adder #(parameter N = 4)
    (input wire [N-1:0] a, b, output reg [N-1:0] sum);

reg [N-1:0] mag_a, mag_b, max, min;
reg sign_a, sign_b, sign_sum;

always @(*)
    begin    
    mag_a = a[N-2:0];
    mag_b = b[N-2:0];

    sign_a = a[N-1]; 
    sign_b = b[N-1];

    if (mag_a > mag_b)
        begin
            max = mag_a;
            min = mag_b;
            sign_sum = sign_a;
        end
    else
        begin
            max = mag_b;
            min = mag_a;
            sign_sum = sign_b;
        end

    if (sign_a == sign_b) begin
        sum[N-2:0] = max + min;
        end
    else begin
        sum[N-2:0] = max - min;
        end
  
    sum[N-1:0] = {sign_sum, sum[N-2:0]};
    
    end  
endmodule

Verilog/Sign Adder/sign_adder_tb.v
`timescale 1ns/1ps
module signed_tb();
    reg [3:0] a;
    reg [3:0] b;
    wire [3:0] sum;
    integer i;

    sign_adder uut (.a(a), .b(b), .sum(sum));
    initial begin
    $monitor("a: %b,b: %b, sum:%b", a, b, sum);
    $dumpfile("sign_adder.vcd");
    $dumpvars(0, signed_tb);
        #10;
        a = 4'h0;
        b = 4'hf;
        for(i=0; i<15; i=i+1) 
        begin          
            a = a + 4'h1 ; 
            b = b - 4'h1;
            #10;
        end
    $finish;
    end
endmodule

Verilog/Sign Adder/sign_adder.vcd
$date
	Fri Aug 25 07:03:38 2023
$end
$version
	Icarus Verilog
$end
$timescale
	1s
$end
$scope module signed_tb $end
$var wire 4 ! sum [3:0] $end
$var reg 4 " a [3:0] $end
$var reg 4 # b [3:0] $end
$var integer 32 $ i [31:0] $end
$scope module uut $end
$var wire 4 % a [3:0] $end
$var wire 4 & b [3:0] $end
$var parameter 32 ' N $end
$var reg 4 ( mag_a [3:0] $end
$var reg 4 ) mag_b [3:0] $end
$var reg 4 * max [3:0] $end
$var reg 4 + min [3:0] $end
$var reg 1 , sign_a $end
$var reg 1 - sign_b $end
$var reg 1 . sign_sum $end
$var reg 4 / sum [3:0] $end
$upscope $end
$upscope $end
$enddefinitions $end
$comment Show the parameter values. $end
$dumpall
b100 '
$end
#0
$dumpvars
bx /
x.
x-
x,
bx +
bx *
bx )
bx (
bx &
bx %
bx $
bx #
bx "
bx !
$end
#10
b1101 !
b1101 /
1.
b1 +
b110 *
1-
0,
b110 )
b1 (
b0 $
b1110 #
b1110 &
b1 "
b1 %
#20
b1011 !
b1011 /
b10 +
b101 *
b101 )
b10 (
b1101 #
b1101 &
b10 "
b10 %
b1 $
#30
b1001 !
b1001 /
b11 +
b100 *
b100 )
b11 (
b1100 #
b1100 &
b11 "
b11 %
b10 $
#40
b1 !
b1 /
0.
b11 )
b100 (
b1011 #
b1011 &
b100 "
b100 %
b11 $
#50
b11 !
b11 /
b10 +
b101 *
b10 )
b101 (
b1010 #
b1010 &
b101 "
b101 %
b100 $
#60
b101 !
b101 /
b1 +
b110 *
b1 )
b110 (
b1001 #
b1001 &
b110 "
b110 %
b101 $
#70
b111 !
b111 /
b0 +
b111 *
b0 )
b111 (
b1000 #
b1000 &
b111 "
b111 %
b110 $
#80
0-
1,
b111 )
b0 (
b111 #
b111 &
b1000 "
b1000 %
b111 $
#90
b101 !
b101 /
b1 +
b110 *
b110 )
b1 (
b110 #
b110 &
b1001 "
b1001 %
b1000 $
#100
b11 !
b11 /
b10 +
b101 *
b101 )
b10 (
b101 #
b101 &
b1010 "
b1010 %
b1001 $
#110
b1 !
b1 /
b11 +
b100 *
b100 )
b11 (
b100 #
b100 &
b1011 "
b1011 %
b1010 $
#120
b1001 !
b1001 /
1.
b11 )
b100 (
b11 #
b11 &
b1100 "
b1100 %
b1011 $
#130
b1011 !
b1011 /
b10 +
b101 *
b10 )
b101 (
b10 #
b10 &
b1101 "
b1101 %
b1100 $
#140
b1101 !
b1101 /
b1 +
b110 *
b1 )
b110 (
b1 #
b1 &
b1110 "
b1110 %
b1101 $
#150
b1111 !
b1111 /
b0 +
b111 *
b0 )
b111 (
b0 #
b0 &
b1111 "
b1111 %
b1110 $
#160
b1111 $
