Verilog/Shift Register/shift_reg.v
`timescale 1ns/1ps
module shift_reg(
    input wire clk,reset,
    input wire[1:0]cntrl,
    input wire[3:0]d,
    output wire[3:0]q
  );

  reg[3:0]r_reg,r_next;
  always@(posedge clk,posedge reset)
    if(reset)
      r_reg<=0;
    else
      r_reg<=r_next;

  always@*
  case(cntrl)
    2'b00:
      r_next=r_reg;
    2'b01:
      r_next={r_reg[2:0],d[0]};
    2'b10:
      r_next={d[3],r_reg[3:1]};
    default:
      r_next=d;
  endcase
  
  assign q=r_reg;
endmodule

Verilog/Shift Register/tb.v
module shift_reg_tb();

reg clk, reset;
reg [1:0] cntrl;
reg [3:0] d;
wire[3:0] q;

shift_reg uut(.clk(clk),.reset(reset),.cntrl(cntrl),.d(d),.q(q));

    initial begin
        
        clk = 0; d = 4'b0001;
        forever #5 clk = ~clk;
    end
        
    initial begin
    
        $dumpfile("shift.vcd");
        $dumpvars(0, shift_reg_tb);
        
        reset = 0;
        #10 cntrl = 2'b01;
        
        #30 cntrl = 2'b10;
        
        #30

    $finish;
    end

endmodule

Verilog/Shift Register/shift.vcd
$date
	Tue Jan 09 21:19:14 2024
$end
$version
	Icarus Verilog
$end
$timescale
	1ps
$end
$scope module shift_reg_tb $end
$var wire 4 ! q [3:0] $end
$var reg 1 " clk $end
$var reg 2 # cntrl [1:0] $end
$var reg 4 $ d [3:0] $end
$var reg 1 % reset $end
$scope module uut $end
$var wire 1 " clk $end
$var wire 2 & cntrl [1:0] $end
$var wire 4 ' d [3:0] $end
$var wire 4 ( q [3:0] $end
$var wire 1 % reset $end
$var reg 4 ) r_next [3:0] $end
$var reg 4 * r_reg [3:0] $end
$upscope $end
$upscope $end
$enddefinitions $end
$comment Show the parameter values. $end
$dumpall
$end
#0
$dumpvars
bx *
b1 )
bx (
b1 '
bx &
0%
b1 $
bx #
0"
bx !
$end
#5000
b1 !
b1 (
b1 *
1"
#10000
b11 )
0"
b1 #
b1 &
#15000
b111 )
b11 !
b11 (
b11 *
1"
#20000
0"
#25000
b1111 )
b111 !
b111 (
b111 *
1"
#30000
0"
#35000
b1111 !
b1111 (
b1111 *
1"
#40000
b111 )
0"
b10 #
b10 &
#45000
b11 )
b111 !
b111 (
b111 *
1"
#50000
0"
#55000
b1 )
b11 !
b11 (
b11 *
1"
#60000
0"
#65000
b0 )
b1 !
b1 (
b1 *
1"
